mediaflowimage/__init__.py
mediaflowimage/admin.py
mediaflowimage/apps.py
mediaflowimage/blocks.py
mediaflowimage/forms.py
mediaflowimage/models.py
mediaflowimage/tests.py
mediaflowimage/views.py
mediaflowimage/wagtail_hooks.py
mediaflowimage/widgets.py
mediaflowimage/migrations/__init__.py
mediaflowimage/static/css/mediaflow-imagechooser-extensions.css
mediaflowimage/static/js/mediaflow-imagechooser-extensions.js
mediaflowimage/templates/widgets/mediaflow-custom-imageinput.html
mediaflowimage-1.0.6.dist-info/METADATA
mediaflowimage-1.0.6.dist-info/WHEEL
mediaflowimage-1.0.6.dist-info/licenses/LICENSE
mediaflowimage-1.0.6.dist-info/RECORD
